README.txt
setup.py
collective/__init__.py
collective.redirect.egg-info/PKG-INFO
collective.redirect.egg-info/SOURCES.txt
collective.redirect.egg-info/dependency_links.txt
collective.redirect.egg-info/entry_points.txt
collective.redirect.egg-info/namespace_packages.txt
collective.redirect.egg-info/not-zip-safe
collective.redirect.egg-info/requires.txt
collective.redirect.egg-info/top_level.txt
collective/redirect/README.txt
collective/redirect/__init__.py
collective/redirect/browser.py
collective/redirect/configure.zcml
collective/redirect/content.py
collective/redirect/testing.py
collective/redirect/tests.py
collective/redirect/profiles/default/catalog.xml
collective/redirect/profiles/default/factorytool.xml
collective/redirect/profiles/default/skins.xml
collective/redirect/profiles/default/types.xml
collective/redirect/profiles/default/types/Redirect.xml
collective/redirect/skins/collective_redirect/standard_error_message.py
docs/HISTORY.txt