Metadata-Version: 1.0
Name: collective.redirect
Version: 0.5
Summary: Administer redirects to internal or external URLs using Link like content
Home-page: http://pypi.python.org/pypi/collective.redirect
Author: Ross Patterson
Author-email: me@rpatterson.net
License: GPL
Platform: UNKNOWN
Classifier: Programming Language :: Python
Classifier: Topic :: Software Development :: Libraries :: Python Modules
